8_report/imem.sv
module imem(input [5:0] pc,output logic [9:0] o);
    always_comb
        case(pc)
        //synopsys full_case parallel_case
        5'h00: o = 10'b0_00_010_00_01;//SET0 r0 <- 0
        5'h01: o = 10'b0_01_001_00_00;//TRU  r1 <- r0
        5'h02: o = 10'b0_00_100_00_01;//SET2 r0 <- 2
        5'h03: o = 10'b0_10_001_00_01;//TRU  r2 <- r1
        5'h04: o = 10'b0_01_001_00_00;//TRU  r1 <- r0
        5'h05: o = 10'b0_00_101_00_01;//SET3 r0 <- 3
        //ここから繰り返し
        5'h06: o = 10'b0_11_000_01_10;//ADD  r3 <- r1 + r2
        5'h07: o = 10'b0_10_001_00_01;//TRU  r2 <- r1
        5'h08: o = 10'b0_01_001_00_00;//TRU  r1 <- r0
        5'h09: o = 10'b0_00_001_00_11;//TRU  r0 <- r3
        5'h0A: o = 10'b0_11_000_01_10;//ADD  r3 <- r1 + r2
        5'h0B: o = 10'b0_10_001_00_01;//TRU  r2 <- r1
        5'h0C: o = 10'b0_01_001_00_00;//TRU  r1 <- r0
        5'h0D: o = 10'b0_00_001_00_11;//TRU  r0 <- r3
        5'h0E: o = 10'b0_11_000_01_10;//ADD  r3 <- r1 + r2
        5'h0F: o = 10'b0_10_001_00_01;//TRU  r2 <- r1
        5'h10: o = 10'b0_01_001_00_00;//TRU  r1 <- r0
        5'h11: o = 10'b0_00_001_00_11;//TRU  r0 <- r3
        5'h12: o = 10'b0_11_000_01_10;//ADD  r3 <- r1 + r2
        5'h13: o = 10'b0_10_001_00_01;//TRU  r2 <- r1
        5'h14: o = 10'b0_01_001_00_00;//TRU  r1 <- r0
        5'h15: o = 10'b0_00_001_00_11;//TRU  r0 <- r3
        5'h16: o = 10'b0_11_000_01_10;//ADD  r3 <- r1 + r2
        5'h17: o = 10'b0_10_001_00_01;//TRU  r2 <- r1
        5'h18: o = 10'b0_01_001_00_00;//TRU  r1 <- r0
        5'h19: o = 10'b0_00_001_00_11;//TRU  r0 <- r3
        5'h1A: o = 10'b0_11_000_01_10;//ADD  r3 <- r1 + r2
        5'h1B: o = 10'b0_10_001_00_01;//TRU  r2 <- r1
        5'h1C: o = 10'b0_01_001_00_00;//TRU  r1 <- r0
        5'h1D: o = 10'b0_00_001_00_11;//TRU  r0 <- r3
        5'h1E: o = 10'b1_11_000_01_10;//ADD  r3 <- r1 + r2
        endcase
endmodule

// enum {ADD, TRU, SET0,SET1,SET2,SET3,SUB} OPTYPE;
//       000  001  010  011  100  101 110
    // assign {h,wad,op,brad,arad} = o;

8_report/pc.sv
module pc(input halt,output logic [5:0] pc,input clk,rst);
    always @(posedge clk or posedge rst)
        if(rst) pc <= 0;
        else if(!halt) pc <= pc + 1;
endmodule

8_report/alu.sv
module alu(input [15:0] a,b,input [2:0] op,output logic [15:0] r);
    enum {ADD, TRU, SET0,SET1,SET2,SET3,SUB} OPTYPE;
    always_comb begin
        case(op)
        //synopsys full_case parallel_case
        ADD: r = a+b;
        TRU: r = a;
        SET0: r = 0;
        SET1: r = 1;
        SET2: r = 2;
        SET3: r = 3;
        SUB: r = a-b;
        endcase
    end
endmodule

8_report/rega.sv
module rega(input logic [1:0] arad,brad, output logic [15:0] a,b,input we,input logic [1:0] wad,input [15:0] wd,input clk,rst);
    logic [15:0] regar [3:0];
    always @(posedge clk or posedge rst) begin
        if(we) begin
            regar[wad] <= wd;
        end
    end
    assign a = regar[arad];
    assign b = regar[brad]; 
endmodule

8_report/top.sv
module top(input clk,rst);
    logic [15:0] a,b,wd;
    logic [1:0] arad,brad,wad;
    logic [2:0] op;
    logic [5:0] pca;
    logic [9:0] o;
    rega rega(arad,brad,a,b,we,wad,wd,clk,rst);
    alu alu(a,b,op,wd);
    pc pc(h,pca,clk,rst);
    imem imem(pca,o);
    assign {h,wad,op,brad,arad} = o;
    assign we = ~h;
endmodule

8_report/test.sv
module test;
    logic clk,rst;
    top top(clk,rst);
    always #5 clk = ~clk;
    initial begin
    $dumpfile("fibo.vcd");
    $dumpvars(0,top);
    rst = 1;
    clk = 0;
    #20
    rst = 0;
    #500
    $finish;
    end
endmodule

8_report/fibo.vcd
$date
	Fri Jun  9 10:41:36 2023
$end
$version
	Icarus Verilog
$end
$timescale
	1s
$end
$scope module test $end
$scope module top $end
$var wire 1 ! clk $end
$var wire 1 " rst $end
$var wire 1 # we $end
$var wire 16 $ wd [15:0] $end
$var wire 2 % wad [1:0] $end
$var wire 6 & pca [5:0] $end
$var wire 3 ' op [2:0] $end
$var wire 10 ( o [9:0] $end
$var wire 1 ) h $end
$var wire 2 * brad [1:0] $end
$var wire 16 + b [15:0] $end
$var wire 2 , arad [1:0] $end
$var wire 16 - a [15:0] $end
$scope module alu $end
$var wire 3 . op [2:0] $end
$var wire 16 / b [15:0] $end
$var wire 16 0 a [15:0] $end
$var reg 16 1 r [15:0] $end
$upscope $end
$scope module imem $end
$var wire 6 2 pc [5:0] $end
$var reg 10 3 o [9:0] $end
$upscope $end
$scope module pc $end
$var wire 1 ! clk $end
$var wire 1 ) halt $end
$var wire 1 " rst $end
$var reg 6 4 pc [5:0] $end
$upscope $end
$scope module rega $end
$var wire 16 5 a [15:0] $end
$var wire 2 6 arad [1:0] $end
$var wire 16 7 b [15:0] $end
$var wire 2 8 brad [1:0] $end
$var wire 1 ! clk $end
$var wire 1 " rst $end
$var wire 2 9 wad [1:0] $end
$var wire 16 : wd [15:0] $end
$var wire 1 # we $end
$upscope $end
$upscope $end
$upscope $end
$enddefinitions $end
#0
$dumpvars
b0 :
b0 9
b0 8
bx 7
b1 6
bx 5
b0 4
b100001 3
b0 2
b0 1
bx 0
bx /
b10 .
bx -
b1 ,
bx +
b0 *
0)
b100001 (
b10 '
b0 &
b0 %
b0 $
1#
1"
0!
$end
#5
b0 +
b0 /
b0 7
1!
#10
0!
#15
1!
#20
0!
0"
#25
b1 %
b1 9
b1 '
b1 .
b0 -
b0 0
b0 5
b0 ,
b0 6
b10010000 (
b10010000 3
b1 &
b1 2
b1 4
1!
#30
0!
#35
b10 $
b10 1
b10 :
b0 %
b0 9
b100 '
b100 .
b1 ,
b1 6
b1000001 (
b1000001 3
b10 &
b10 2
b10 4
1!
#40
0!
#45
b0 $
b0 1
b0 :
b10 %
b10 9
b1 '
b1 .
b100010001 (
b100010001 3
b11 &
b11 2
b11 4
b10 +
b10 /
b10 7
1!
#50
0!
#55
b10 $
b10 1
b10 :
b1 %
b1 9
b10 -
b10 0
b10 5
b0 ,
b0 6
b10010000 (
b10010000 3
b100 &
b100 2
b100 4
1!
#60
0!
#65
b11 $
b11 1
b11 :
b0 %
b0 9
b101 '
b101 .
b1 ,
b1 6
b1010001 (
b1010001 3
b101 &
b101 2
b101 4
1!
#70
0!
#75
b10 $
b10 1
b10 :
b11 %
b11 9
b0 '
b0 .
b1 *
b1 8
b0 -
b0 0
b0 5
b10 ,
b10 6
b110000110 (
b110000110 3
b10 +
b10 /
b10 7
b110 &
b110 2
b110 4
1!
#80
0!
#85
b10 %
b10 9
b1 '
b1 .
b11 +
b11 /
b11 7
b0 *
b0 8
b10 -
b10 0
b10 5
b1 ,
b1 6
b100010001 (
b100010001 3
b111 &
b111 2
b111 4
1!
#90
0!
#95
b11 $
b11 1
b11 :
b1 %
b1 9
b11 -
b11 0
b11 5
b0 ,
b0 6
b10010000 (
b10010000 3
b1000 &
b1000 2
b1000 4
1!
#100
0!
#105
b10 $
b10 1
b10 :
b0 %
b0 9
b10 -
b10 0
b10 5
b11 ,
b11 6
b10011 (
b10011 3
b1001 &
b1001 2
b1001 4
1!
#110
0!
#115
b101 $
b101 1
b101 :
b11 %
b11 9
b0 '
b0 .
b1 *
b1 8
b10 ,
b10 6
b110000110 (
b110000110 3
b11 +
b11 /
b11 7
b1010 &
b1010 2
b1010 4
1!
#120
0!
#125
b11 $
b11 1
b11 :
b10 %
b10 9
b1 '
b1 .
b10 +
b10 /
b10 7
b0 *
b0 8
b11 -
b11 0
b11 5
b1 ,
b1 6
b100010001 (
b100010001 3
b1011 &
b1011 2
b1011 4
1!
#130
0!
#135
b10 $
b10 1
b10 :
b1 %
b1 9
b10 -
b10 0
b10 5
b0 ,
b0 6
b10010000 (
b10010000 3
b1100 &
b1100 2
b1100 4
1!
#140
0!
#145
b101 $
b101 1
b101 :
b0 %
b0 9
b101 -
b101 0
b101 5
b11 ,
b11 6
b10011 (
b10011 3
b1101 &
b1101 2
b1101 4
1!
#150
0!
#155
b11 %
b11 9
b0 '
b0 .
b1 *
b1 8
b11 -
b11 0
b11 5
b10 ,
b10 6
b110000110 (
b110000110 3
b10 +
b10 /
b10 7
b1110 &
b1110 2
b1110 4
1!
#160
0!
#165
b10 $
b10 1
b10 :
b10 %
b10 9
b1 '
b1 .
b101 +
b101 /
b101 7
b0 *
b0 8
b10 -
b10 0
b10 5
b1 ,
b1 6
b100010001 (
b100010001 3
b1111 &
b1111 2
b1111 4
1!
#170
0!
#175
b101 $
b101 1
b101 :
b1 %
b1 9
b101 -
b101 0
b101 5
b0 ,
b0 6
b10010000 (
b10010000 3
b10000 &
b10000 2
b10000 4
1!
#180
0!
#185
b0 %
b0 9
b11 ,
b11 6
b10011 (
b10011 3
b10001 &
b10001 2
b10001 4
1!
#190
0!
#195
b111 $
b111 1
b111 :
b11 %
b11 9
b0 '
b0 .
b1 *
b1 8
b10 -
b10 0
b10 5
b10 ,
b10 6
b110000110 (
b110000110 3
b10010 &
b10010 2
b10010 4
1!
#200
0!
#205
b101 $
b101 1
b101 :
b10 %
b10 9
b1 '
b1 .
b0 *
b0 8
b101 -
b101 0
b101 5
b1 ,
b1 6
b100010001 (
b100010001 3
b10011 &
b10011 2
b10011 4
1!
#210
0!
#215
b1 %
b1 9
b0 ,
b0 6
b10010000 (
b10010000 3
b10100 &
b10100 2
b10100 4
1!
#220
0!
#225
b111 $
b111 1
b111 :
b0 %
b0 9
b111 -
b111 0
b111 5
b11 ,
b11 6
b10011 (
b10011 3
b10101 &
b10101 2
b10101 4
1!
#230
0!
#235
b1010 $
b1010 1
b1010 :
b11 %
b11 9
b0 '
b0 .
b1 *
b1 8
b101 -
b101 0
b101 5
b10 ,
b10 6
b110000110 (
b110000110 3
b101 +
b101 /
b101 7
b10110 &
b10110 2
b10110 4
1!
#240
0!
#245
b101 $
b101 1
b101 :
b10 %
b10 9
b1 '
b1 .
b111 +
b111 /
b111 7
b0 *
b0 8
b1 ,
b1 6
b100010001 (
b100010001 3
b10111 &
b10111 2
b10111 4
1!
#250
0!
#255
b111 $
b111 1
b111 :
b1 %
b1 9
b111 -
b111 0
b111 5
b0 ,
b0 6
b10010000 (
b10010000 3
b11000 &
b11000 2
b11000 4
1!
#260
0!
#265
b1010 $
b1010 1
b1010 :
b0 %
b0 9
b1010 -
b1010 0
b1010 5
b11 ,
b11 6
b10011 (
b10011 3
b11001 &
b11001 2
b11001 4
1!
#270
0!
#275
b1100 $
b1100 1
b1100 :
b11 %
b11 9
b0 '
b0 .
b1 *
b1 8
b101 -
b101 0
b101 5
b10 ,
b10 6
b110000110 (
b110000110 3
b111 +
b111 /
b111 7
b11010 &
b11010 2
b11010 4
1!
#280
0!
#285
b111 $
b111 1
b111 :
b10 %
b10 9
b1 '
b1 .
b1010 +
b1010 /
b1010 7
b0 *
b0 8
b111 -
b111 0
b111 5
b1 ,
b1 6
b100010001 (
b100010001 3
b11011 &
b11011 2
b11011 4
1!
#290
0!
#295
b1010 $
b1010 1
b1010 :
b1 %
b1 9
b1010 -
b1010 0
b1010 5
b0 ,
b0 6
b10010000 (
b10010000 3
b11100 &
b11100 2
b11100 4
1!
#300
0!
#305
b1100 $
b1100 1
b1100 :
b0 %
b0 9
b1100 -
b1100 0
b1100 5
b11 ,
b11 6
b10011 (
b10011 3
b11101 &
b11101 2
b11101 4
1!
#310
0!
#315
0#
b10001 $
b10001 1
b10001 :
1)
b11 %
b11 9
b0 '
b0 .
b1 *
b1 8
b111 -
b111 0
b111 5
b10 ,
b10 6
b1110000110 (
b1110000110 3
b1010 +
b1010 /
b1010 7
b11110 &
b11110 2
b11110 4
1!
