4_report/chat.sv
module chat(input in,clk,rst,output logic out);
    logic [3:0] count;
    logic val; 

    always_ff @(negedge clk) begin
        if(rst) val <= 0;
        else begin
            if(!in) val <= 1;
            else val <= val;
        end
    end

    always_ff @(negedge clk) begin
        if(rst) count <= 4'b1111;
        else if(val) begin
            if(count != 0) count <= count - 1;            
            else count <= count;
        end
    end

    always_comb begin
        if(count==0 || count ==4'b1111) out = in; //counterが始動する前or終了した後はinをそのまま出力
        else out = 0; //counterが動いている間は0を出力
    end

endmodule

4_report/test.sv
module test;
    logic in,clk,rst;
    logic out;
    always #5 clk = ~clk;
    chat chat(in,clk,rst,out);
    initial begin  
        $dumpfile("chat.vcd");
        $dumpvars(0,test);
        in = 1;
        clk = 0;
        rst = 1;
        #10
        rst = 0;
        in = 1;
        #10
        in = 0;
        #10
        in = 1;
        #10
        in = 0;
        #10
        in = 1;
        #10
        in = 1;
        #10
        in = 1;
        #10
        in = 0;
        #10
        in = 1;
        #10
        in = 1;
        #10
        in = 1;
        #10
        in = 0;
        #10
        in = 1;
        #10
        in = 1;
        #10
        in = 1;
        #10
        in = 0;
        #10
        in = 0;
        #10
        in = 0;
        #10
        in = 0;
        #10
        in = 0;
        #10
        in = 0;
        #10
        in = 0;
        #10
        in = 1;
        rst = 1;
        #10
        in = 1;
        rst = 0;
        #10
        in = 1;
        #10
        in = 1;
        #10
        in = 0;
        #10
        in = 0;
        #10
        in = 1;
        #10
        in = 0;
        #10
        in = 0;
        $finish;
    end
endmodule

4_report/chat.vcd
$date
	Mon May  8 15:42:12 2023
$end
$version
	Icarus Verilog
$end
$timescale
	1s
$end
$scope module test $end
$var wire 1 ! out $end
$var reg 1 " clk $end
$var reg 1 # in $end
$var reg 1 $ rst $end
$scope module chat $end
$var wire 1 " clk $end
$var wire 1 # in $end
$var wire 1 $ rst $end
$var reg 4 % count [3:0] $end
$var reg 1 ! out $end
$var reg 1 & val $end
$upscope $end
$upscope $end
$enddefinitions $end
#0
$dumpvars
0&
b1111 %
1$
1#
0"
1!
$end
#5
1"
#10
0"
0$
#15
1"
#20
1&
0!
0"
0#
#25
1"
#30
b1110 %
0!
0"
1#
#35
1"
#40
b1101 %
0"
0#
#45
1"
#50
b1100 %
0"
1#
#55
1"
#60
b1011 %
0"
#65
1"
#70
b1010 %
0"
#75
1"
#80
b1001 %
0"
0#
#85
1"
#90
b1000 %
0"
1#
#95
1"
#100
b111 %
0"
#105
1"
#110
b110 %
0"
#115
1"
#120
b101 %
0"
0#
#125
1"
#130
b100 %
0"
1#
#135
1"
#140
b11 %
0"
#145
1"
#150
b10 %
0"
#155
1"
#160
b1 %
0"
0#
#165
1"
#170
b0 %
0"
#175
1"
#180
0"
#185
1"
#190
0"
#195
1"
#200
0"
#205
1"
#210
0"
#215
1"
#220
0"
#225
1"
#230
b1111 %
0&
1!
0"
1$
1#
#235
1"
#240
0"
0$
#245
1"
#250
0"
#255
1"
#260
0"
#265
1"
#270
1&
0!
0"
0#
#275
1"
#280
b1110 %
0"
#285
1"
#290
b1101 %
0"
1#
#295
1"
#300
b1100 %
0"
0#
#305
1"
#310
b1011 %
0"
