6_report/venmac.sv
module venmac (a,b,can,coin,clk,rst);
    input a,b,clk,rst;
    output logic can;
    output logic [3:0] coin;

    logic [3:0] state,nstate;

    always_ff @(posedge clk) begin
        if(rst) state <= 4'b0000;
        else state <= nstate;
    end

    always_comb begin
        nstate = state;
        can = 0;
        if(a == 1) begin
            case(state)
            //synopsys full_case parallel_case
                4'b0000: begin
                    nstate = 4'b0001;
                    coin = 4'b0000;
                end
                4'b0001: nstate = 4'b0010;
                4'b0010: nstate = 4'b0011;
                4'b0011: nstate = 4'b0100;
                4'b0100: nstate = 4'b0101;
                4'b0101: can = 1;
            endcase
        end
        if(b == 1) begin
            case(state)
                4'b0000: begin
                    can =0;
                    nstate=4'b0101;
                    coin = 4'b0000;
                end
                4'b0001: begin
                    can =1;
                    nstate=4'b0110;
                    coin = 4'b0001;
                end
                4'b0010: begin
                    can =1;
                    nstate=4'b0111;
                    coin = 4'b0010; 
                end
                4'b0011: begin
                    can =1;
                    nstate=4'b1000;
                    coin = 4'b0011; 
                end            
                4'b0100: begin
                    can =1;
                    nstate=4'b1001;
                    coin = 4'b0100; 
                end 
            endcase
        end
    end
endmodule

6_report/test.sv
`timescale 1ns/10ps
module test;
    reg a,b,rst;
    wire can;
    reg clk;
    wire [3:0] coin;
    always #5 clk =~clk;
    venmac venmac(a,b,can,coin,clk,rst);
    initial begin
    $dumpfile("state.vcd");
    $dumpvars(0,test);
    clk=0;
    rst=1;
    a=0;
    b=0;
#20
    rst =0;
#10
    a=1;
    b=0;
#10
    a=0;
    b=0;
#10
    a=1;
    b=0;
#10
    a=0;
    b=0;
#10
    a=1;
    b=0;
#10
    a=0;
    b=0;
#10
    a=1;
    b=0;
#10
    a=0;
    b=0;
#10
    a=1;
    b=0;
#10
    a=0;
    b=0;
#40
    rst=1;
#20
    rst=0;
#10
    a=0;
    b=0;
#10
    a=1;
    b=0;
#10
    a=0;
    b=0;
#10
    a=0;
    b=1;
#10
    a=0;
    b=0;
#40
    rst=1;
#20
    rst=0;
#10
    a=0;
    b=0;
#10
    a=1;
    b=0;
#10
    a=0;
    b=0;
    #10
    a=1;
    b=0;
#10
    a=0;
    b=0;
    #10
    a=1;
    b=0;
#10
    a=0;
    b=0;
#10
    a=0;
    b=1;
#10
    a=0;
    b=0;
#50
    $finish;
    end
endmodule

6_report/state.vcd
$date
	Fri May 19 10:20:37 2023
$end
$version
	Icarus Verilog
$end
$timescale
	10ps
$end
$scope module test $end
$var wire 4 ! coin [3:0] $end
$var wire 1 " can $end
$var reg 1 # a $end
$var reg 1 $ b $end
$var reg 1 % clk $end
$var reg 1 & rst $end
$scope module venmac $end
$var wire 1 # a $end
$var wire 1 $ b $end
$var wire 1 % clk $end
$var wire 1 & rst $end
$var reg 1 " can $end
$var reg 4 ' coin [3:0] $end
$var reg 4 ( nstate [3:0] $end
$var reg 4 ) state [3:0] $end
$upscope $end
$upscope $end
$enddefinitions $end
#0
$dumpvars
bx )
bx (
bx '
1&
0%
0$
0#
0"
bx !
$end
#500
b0 (
b0 )
1%
#1000
0%
#1500
1%
#2000
0%
0&
#2500
1%
#3000
b0 !
b0 '
b1 (
0%
1#
#3500
b10 (
b1 )
1%
#4000
b1 (
0%
0#
#4500
1%
#5000
b10 (
0%
1#
#5500
b11 (
b10 )
1%
#6000
b10 (
0%
0#
#6500
1%
#7000
b11 (
0%
1#
#7500
b100 (
b11 )
1%
#8000
b11 (
0%
0#
#8500
1%
#9000
b100 (
0%
1#
#9500
b101 (
b100 )
1%
#10000
b100 (
0%
0#
#10500
1%
#11000
b101 (
0%
1#
#11500
1"
b101 )
1%
#12000
0"
0%
0#
#12500
1%
#13000
0%
#13500
1%
#14000
0%
#14500
1%
#15000
0%
#15500
1%
#16000
0%
1&
#16500
b0 (
b0 )
1%
#17000
0%
#17500
1%
#18000
0%
0&
#18500
1%
#19000
0%
#19500
1%
#20000
b1 (
0%
1#
#20500
b10 (
b1 )
1%
#21000
b1 (
0%
0#
#21500
1%
#22000
b1 !
b1 '
b110 (
1"
0%
1$
#22500
0"
b110 )
1%
#23000
0%
0$
#23500
1%
#24000
0%
#24500
1%
#25000
0%
#25500
1%
#26000
0%
#26500
1%
#27000
0%
1&
#27500
b0 (
b0 )
1%
#28000
0%
#28500
1%
#29000
0%
0&
#29500
1%
#30000
0%
#30500
1%
#31000
b0 !
b0 '
b1 (
0%
1#
#31500
b10 (
b1 )
1%
#32000
b1 (
0%
0#
#32500
1%
#33000
b10 (
0%
1#
#33500
b11 (
b10 )
1%
#34000
b10 (
0%
0#
#34500
1%
#35000
b11 (
0%
1#
#35500
b100 (
b11 )
1%
#36000
b11 (
0%
0#
#36500
1%
#37000
b11 !
b11 '
b1000 (
1"
0%
1$
#37500
0"
b1000 )
1%
#38000
0%
0$
