5_report/fifo.v
module fifo(in, we, full, out, re, empty, clk, rst);
	input [7:0] in;
	input we;
	output logic full;
	output [7:0] out;
	input re;
	output logic empty;
	input clk, rst;
	logic [7:0] mem[7:0];
	logic [2:0] head, tail, headi;
	logic [7:0] out;

	always_ff @(posedge clk) begin
		if(rst) begin
			head <= 0;
			tail <= 0;
		end else begin
			if(we && ~full) begin
				head <= head + 1;
				mem[head] <= in;
			end 
			if(re && ~empty) begin
				tail <= tail + 1;
				out <= mem[tail];
			end else begin
				out <= 0;
			end
		end
	end

	always_comb begin
		headi = head + 1;
		if(head == tail) empty = 1'b1;
		else empty = 1'b0;
		if(headi == tail) full = 1'b1;
		else full = 1'b0;
	end

endmodule

5_report/fifotest.v
module fifotest;
	logic [7:0] in, out;
	logic we, re;
	logic clk, rst;
	fifo fifo(in, we, full, out, re, empty, clk, rst);
	always #5 clk = ~clk;
initial begin
$dumpfile("fifo.vcd");
$dumpvars(0, fifotest);
rst = 1;
clk = 0;
we = 0;
re = 0;
in = 5;
#30;
rst = 0;
we = 1;
#10;
in = 6;
#10;
in = 7;
#10
we = 0;
#10
re = 1;
#10
re = 0;
we = 1;
in = 8;
#10
in = 9;
#10
in = 10;
#10
in = 11;
#10
in = 12;
#10
in = 13;
#10
in = 14;
#10
in = 15;
re = 1;
#10
in = 16;
#50
$finish;
end
endmodule

5_report/fifo.vcd
$date
	Thu May 18 14:20:32 2023
$end
$version
	Icarus Verilog
$end
$timescale
	1s
$end
$scope module fifotest $end
$var wire 8 ! out [7:0] $end
$var wire 1 " full $end
$var wire 1 # empty $end
$var reg 1 $ clk $end
$var reg 8 % in [7:0] $end
$var reg 1 & re $end
$var reg 1 ' rst $end
$var reg 1 ( we $end
$scope module fifo $end
$var wire 1 $ clk $end
$var wire 8 ) in [7:0] $end
$var wire 1 & re $end
$var wire 1 ' rst $end
$var wire 1 ( we $end
$var reg 1 # empty $end
$var reg 1 " full $end
$var reg 3 * head [2:0] $end
$var reg 3 + headi [2:0] $end
$var reg 8 , out [7:0] $end
$var reg 3 - tail [2:0] $end
$upscope $end
$upscope $end
$enddefinitions $end
#0
$dumpvars
bx -
bx ,
bx +
bx *
b101 )
0(
1'
0&
b101 %
0$
0#
0"
bx !
$end
#5
1#
b1 +
b0 -
b0 *
1$
#10
0$
#15
1$
#20
0$
#25
1$
#30
0$
1(
0'
#35
0#
b10 +
b0 !
b0 ,
b1 *
1$
#40
0$
b110 %
b110 )
#45
b11 +
b10 *
1$
#50
0$
b111 %
b111 )
#55
b100 +
b11 *
1$
#60
0$
0(
#65
1$
#70
0$
1&
#75
b101 !
b101 ,
b1 -
1$
#80
0$
b1000 %
b1000 )
1(
0&
#85
b101 +
b0 !
b0 ,
b100 *
1$
#90
0$
b1001 %
b1001 )
#95
b110 +
b101 *
1$
#100
0$
b1010 %
b1010 )
#105
b111 +
b110 *
1$
#110
0$
b1011 %
b1011 )
#115
b0 +
b111 *
1$
#120
0$
b1100 %
b1100 )
#125
1"
b1 +
b0 *
1$
#130
0$
b1101 %
b1101 )
#135
1$
#140
0$
b1110 %
b1110 )
#145
1$
#150
0$
1&
b1111 %
b1111 )
#155
0"
b110 !
b110 ,
b10 -
1$
#160
0$
b10000 %
b10000 )
#165
b10 +
b111 !
b111 ,
b11 -
b1 *
1$
#170
0$
#175
b11 +
b1000 !
b1000 ,
b100 -
b10 *
1$
#180
0$
#185
b100 +
b1001 !
b1001 ,
b101 -
b11 *
1$
#190
0$
#195
b101 +
b1010 !
b1010 ,
b110 -
b100 *
1$
#200
0$
#205
b110 +
b1011 !
b1011 ,
b111 -
b101 *
1$
