7_report/chika.sv
// 次のmoduleの合成上の誤りを直せ
module ex(
    input a, 
    output logic b, 
    input clk, 
    input rst
    );
    logic [1:0] s,ns;
    always @(posedge clk) begin
        if(rst) begin
            s <= 0;
            // b <= 0;
        end else begin
            s <= ns;
        end
    end
    always @* begin
        b = 0;
        ns = s;
        case(s)
            2'b00:begin
                b = 1;
                ns = 2'b01;
            end
            2'b01:begin
                b = 0;
                if(a) ns = 2'b00;
                else ns = 2'b11;
            end
            2'b11:begin
                if(a) b = 1;
                else b = 0;
                ns = 2'b00;
            end
        endcase
    end
endmodule

7_report/test.sv
module test;
	logic a, b;
	logic clk, rst;
	ex ex(a, b, clk, rst);
	always #5 clk = ~clk;
initial begin
	$dumpfile("*.vcd");
	$dumpvars(0, test);
clk = 0;
rst = 1;
a= 0;
#20
rst = 0;
#10
a= 1;
#50
a = 0;
#50
$finish;
end
endmodule

7_report/*.vcd
$date
	Fri May 26 10:58:46 2023
$end
$version
	Icarus Verilog
$end
$timescale
	1s
$end
$scope module test $end
$var wire 1 ! b $end
$var reg 1 " a $end
$var reg 1 # clk $end
$var reg 1 $ rst $end
$scope module ex $end
$var wire 1 " a $end
$var wire 1 # clk $end
$var wire 1 $ rst $end
$var reg 1 ! b $end
$var reg 2 % ns [1:0] $end
$var reg 2 & s [1:0] $end
$upscope $end
$upscope $end
$enddefinitions $end
#0
$dumpvars
bx &
bx %
1$
0#
0"
0!
$end
#5
1!
b1 %
b0 &
1#
#10
0#
#15
1#
#20
0#
0$
#25
b11 %
0!
b1 &
1#
#30
b0 %
0#
1"
#35
b1 %
1!
b0 &
1#
#40
0#
#45
b0 %
0!
b1 &
1#
#50
0#
#55
b1 %
1!
b0 &
1#
#60
0#
#65
b0 %
0!
b1 &
1#
#70
0#
#75
b1 %
1!
b0 &
1#
#80
b1 %
1!
0#
0"
#85
b11 %
0!
b1 &
1#
#90
0#
#95
b0 %
b11 &
1#
#100
0#
#105
b1 %
1!
b0 &
1#
#110
0#
#115
b11 %
0!
b1 &
1#
#120
0#
#125
b0 %
b11 &
1#
